core/__init__.py
core/all_requests.py
core/config.py
core/error_handler.py
core/importer.py
core/utils.py
plugins/__init__.py
Framework_Callisto-0.0.1.dist-info/METADATA
Framework_Callisto-0.0.1.dist-info/WHEEL
Framework_Callisto-0.0.1.dist-info/top_level.txt
Framework_Callisto-0.0.1.dist-info/RECORD
