Metadata-Version: 2.1
Name: Framework-Callisto
Version: 0.0.1
Summary: Testing Framework
Author: Ahmed Bada
Author-email: <dexterhk01@gmail.com>
Keywords: python,Tesint,API,Jupyter,Notebook,Callisto
Classifier: Development Status :: 1 - Planning
Classifier: Intended Audience :: Developers
Classifier: Programming Language :: Python :: 3
Classifier: Operating System :: Unix
Classifier: Operating System :: MacOS :: MacOS X
Classifier: Operating System :: Microsoft :: Windows
Requires-Dist: requests
Requires-Dist: ipywidgets
